{
  "apiVersion": "1.0",
  "data": {
    "updated": 20140808175950,
    "totalItems": 20,
    "currentItemCount": 20,
    "items": [
      {
        "kind": "Imaging",
        "facilityCode": "500",
        "facilityName": "CAMP MASTER",
        "orderName": "SINUSES 3 OR MORE VIEWS",
        "statusName": "COMPLETE",
        "encounterUid": "urn:va:visit:9E7A:224:3820",
        "imagingTypeUid": "urn:va:imaging-Type:GENERAL RADIOLOGY",
        "locationUid": "urn:va:location:9E7A:40",
        "hasImages": false,
        "imageLocation": "RADIOLOGY MAIN FLOOR",
        "uid": "urn:va:image:9E7A:224:6959598.8899-1",
        "summary": "RADIOLOGIC EXAMINATION, SINUSES, PARANASAL, COMPLETE, MINIMUM OF 3 VIEWS",
        "pid": "C877;224",
        "localId": "6959598.8899-1",
        "typeName": "RADIOLOGIC EXAMINATION, SINUSES, PARANASAL, COMPLETE, MINIMUM OF 3 VIEWS",
        "dateTime": "200404011100",
        "category": "RA",
        "reason": "",
        "orderUid": "urn:va:order:9E7A:224:15740",
        "providers": [
          {
            "providerName": "LABTECH,SPECIAL",
            "providerDisplayName": "Labtech,Special",
            "summary": "ProcedureProvider{uid='null'}",
            "providerUid": "urn:va:user:9E7A:11745"
          }
        ],
        "providerName": "LABTECH,SPECIAL",
        "providerDisplayName": "Labtech,Special",
        "results": [
          {
            "localTitle": "SINUSES 3 OR MORE VIEWS",
            "uid": "urn:va:document:9E7A:224:6959598.8899-1",
            "summary": "ProcedureResult{uid='urn:va:document:9E7A:224:6959598.8899-1'}"
          }
        ],
        "verified": true,
        "name": "SINUSES 3 OR MORE VIEWS",
        "diagnosis": [
          {
            "code": "NORMAL",
            "primary": true
          }
        ],
        "locationName": "RADIOLOGY MAIN FLOOR",
        "case": 47,
        "encounterName": "RADIOLOGY MAIN FLOOR Apr 01, 2004"
      },
      {
        "kind": "Imaging",
        "facilityCode": "500",
        "facilityName": "CAMP BEE",
        "orderName": "SINUSES 3 OR MORE VIEWS",
        "statusName": "COMPLETE",
        "encounterUid": "urn:va:visit:C877:224:3820",
        "imagingTypeUid": "urn:va:imaging-Type:GENERAL RADIOLOGY",
        "locationUid": "urn:va:location:C877:40",
        "hasImages": false,
        "imageLocation": "RADIOLOGY MAIN FLOOR",
        "uid": "urn:va:image:C877:224:6959598.8899-1",
        "summary": "RADIOLOGIC EXAMINATION, SINUSES, PARANASAL, COMPLETE, MINIMUM OF 3 VIEWS",
        "pid": "C877;224",
        "localId": "6959598.8899-1",
        "typeName": "RADIOLOGIC EXAMINATION, SINUSES, PARANASAL, COMPLETE, MINIMUM OF 3 VIEWS",
        "dateTime": "200404011100",
        "category": "RA",
        "reason": "",
        "orderUid": "urn:va:order:C877:224:15740",
        "providers": [
          {
            "providerName": "LABTECH,SPECIAL",
            "providerDisplayName": "Labtech,Special",
            "summary": "ProcedureProvider{uid='null'}",
            "providerUid": "urn:va:user:C877:11745"
          }
        ],
        "providerName": "LABTECH,SPECIAL",
        "providerDisplayName": "Labtech,Special",
        "results": [
          {
            "localTitle": "SINUSES 3 OR MORE VIEWS",
            "uid": "urn:va:document:C877:224:6959598.8899-1",
            "summary": "ProcedureResult{uid='urn:va:document:C877:224:6959598.8899-1'}"
          }
        ],
        "verified": true,
        "name": "SINUSES 3 OR MORE VIEWS",
        "diagnosis": [
          {
            "code": "NORMAL",
            "primary": true
          }
        ],
        "locationName": "RADIOLOGY MAIN FLOOR",
        "case": 47,
        "encounterName": "RADIOLOGY MAIN FLOOR Apr 01, 2004"
      },
      {
        "kind": "Imaging",
        "facilityCode": "500",
        "facilityName": "CAMP MASTER",
        "orderName": "SPINE LUMBOSACRAL MIN 2 VIEWS",
        "statusName": "COMPLETE",
        "encounterUid": "urn:va:visit:9E7A:224:3819",
        "imagingTypeUid": "urn:va:imaging-Type:GENERAL RADIOLOGY",
        "locationUid": "urn:va:location:9E7A:40",
        "hasImages": false,
        "imageLocation": "RADIOLOGY MAIN FLOOR",
        "uid": "urn:va:image:9E7A:224:6959668.8599-1",
        "summary": "RADIOLOGIC EXAMINATION, SPINE, LUMBOSACRAL; 2 OR 3 VIEWS",
        "pid": "C877;224",
        "localId": "6959668.8599-1",
        "typeName": "RADIOLOGIC EXAMINATION, SPINE, LUMBOSACRAL; 2 OR 3 VIEWS",
        "dateTime": "200403311400",
        "category": "RA",
        "reason": "",
        "orderUid": "urn:va:order:9E7A:224:15739",
        "providers": [
          {
            "providerName": "LABTECH,SPECIAL",
            "providerDisplayName": "Labtech,Special",
            "summary": "ProcedureProvider{uid='null'}",
            "providerUid": "urn:va:user:9E7A:11745"
          }
        ],
        "providerName": "LABTECH,SPECIAL",
        "providerDisplayName": "Labtech,Special",
        "results": [
          {
            "localTitle": "SPINE LUMBOSACRAL MIN 2 VIEWS",
            "uid": "urn:va:document:9E7A:224:6959668.8599-1",
            "summary": "ProcedureResult{uid='urn:va:document:9E7A:224:6959668.8599-1'}"
          }
        ],
        "verified": true,
        "name": "SPINE LUMBOSACRAL MIN 2 VIEWS",
        "diagnosis": [
          {
            "code": "NORMAL",
            "primary": true
          }
        ],
        "locationName": "RADIOLOGY MAIN FLOOR",
        "case": 46,
        "encounterName": "RADIOLOGY MAIN FLOOR Mar 31, 2004"
      },
      {
        "kind": "Imaging",
        "facilityCode": "500",
        "facilityName": "CAMP BEE",
        "orderName": "SPINE LUMBOSACRAL MIN 2 VIEWS",
        "statusName": "COMPLETE",
        "encounterUid": "urn:va:visit:C877:224:3819",
        "imagingTypeUid": "urn:va:imaging-Type:GENERAL RADIOLOGY",
        "locationUid": "urn:va:location:C877:40",
        "hasImages": false,
        "imageLocation": "RADIOLOGY MAIN FLOOR",
        "uid": "urn:va:image:C877:224:6959668.8599-1",
        "summary": "RADIOLOGIC EXAMINATION, SPINE, LUMBOSACRAL; 2 OR 3 VIEWS",
        "pid": "C877;224",
        "localId": "6959668.8599-1",
        "typeName": "RADIOLOGIC EXAMINATION, SPINE, LUMBOSACRAL; 2 OR 3 VIEWS",
        "dateTime": "200403311400",
        "category": "RA",
        "reason": "",
        "orderUid": "urn:va:order:C877:224:15739",
        "providers": [
          {
            "providerName": "LABTECH,SPECIAL",
            "providerDisplayName": "Labtech,Special",
            "summary": "ProcedureProvider{uid='null'}",
            "providerUid": "urn:va:user:C877:11745"
          }
        ],
        "providerName": "LABTECH,SPECIAL",
        "providerDisplayName": "Labtech,Special",
        "results": [
          {
            "localTitle": "SPINE LUMBOSACRAL MIN 2 VIEWS",
            "uid": "urn:va:document:C877:224:6959668.8599-1",
            "summary": "ProcedureResult{uid='urn:va:document:C877:224:6959668.8599-1'}"
          }
        ],
        "verified": true,
        "name": "SPINE LUMBOSACRAL MIN 2 VIEWS",
        "diagnosis": [
          {
            "code": "NORMAL",
            "primary": true
          }
        ],
        "locationName": "RADIOLOGY MAIN FLOOR",
        "case": 46,
        "encounterName": "RADIOLOGY MAIN FLOOR Mar 31, 2004"
      },
      {
        "kind": "Imaging",
        "facilityCode": "500",
        "facilityName": "CAMP MASTER",
        "orderName": "ESOPHAGUS",
        "statusName": "COMPLETE",
        "encounterUid": "urn:va:visit:9E7A:224:3816",
        "imagingTypeUid": "urn:va:imaging-Type:GENERAL RADIOLOGY",
        "locationUid": "urn:va:location:9E7A:40",
        "hasImages": false,
        "imageLocation": "RADIOLOGY MAIN FLOOR",
        "uid": "urn:va:image:9E7A:224:6959884.8699-1",
        "summary": "RADIOLOGIC EXAMINATION; ESOPHAGUS",
        "pid": "C877;224",
        "localId": "6959884.8699-1",
        "typeName": "RADIOLOGIC EXAMINATION; ESOPHAGUS",
        "dateTime": "200401151300",
        "category": "RA",
        "reason": "",
        "orderUid": "urn:va:order:9E7A:224:15737",
        "providers": [
          {
            "providerName": "LABTECH,SPECIAL",
            "providerDisplayName": "Labtech,Special",
            "summary": "ProcedureProvider{uid='null'}",
            "providerUid": "urn:va:user:9E7A:11745"
          }
        ],
        "providerName": "LABTECH,SPECIAL",
        "providerDisplayName": "Labtech,Special",
        "results": [
          {
            "localTitle": "ESOPHAGUS",
            "uid": "urn:va:document:9E7A:224:6959884.8699-1",
            "summary": "ProcedureResult{uid='urn:va:document:9E7A:224:6959884.8699-1'}"
          }
        ],
        "verified": true,
        "name": "ESOPHAGUS",
        "diagnosis": [
          {
            "code": "NORMAL",
            "primary": true
          }
        ],
        "locationName": "RADIOLOGY MAIN FLOOR",
        "case": 43,
        "encounterName": "RADIOLOGY MAIN FLOOR Jan 15, 2004"
      },
      {
        "kind": "Imaging",
        "facilityCode": "500",
        "facilityName": "CAMP BEE",
        "orderName": "ESOPHAGUS",
        "statusName": "COMPLETE",
        "encounterUid": "urn:va:visit:C877:224:3816",
        "imagingTypeUid": "urn:va:imaging-Type:GENERAL RADIOLOGY",
        "locationUid": "urn:va:location:C877:40",
        "hasImages": false,
        "imageLocation": "RADIOLOGY MAIN FLOOR",
        "uid": "urn:va:image:C877:224:6959884.8699-1",
        "summary": "RADIOLOGIC EXAMINATION; ESOPHAGUS",
        "pid": "C877;224",
        "localId": "6959884.8699-1",
        "typeName": "RADIOLOGIC EXAMINATION; ESOPHAGUS",
        "dateTime": "200401151300",
        "category": "RA",
        "reason": "",
        "orderUid": "urn:va:order:C877:224:15737",
        "providers": [
          {
            "providerName": "LABTECH,SPECIAL",
            "providerDisplayName": "Labtech,Special",
            "summary": "ProcedureProvider{uid='null'}",
            "providerUid": "urn:va:user:C877:11745"
          }
        ],
        "providerName": "LABTECH,SPECIAL",
        "providerDisplayName": "Labtech,Special",
        "results": [
          {
            "localTitle": "ESOPHAGUS",
            "uid": "urn:va:document:C877:224:6959884.8699-1",
            "summary": "ProcedureResult{uid='urn:va:document:C877:224:6959884.8699-1'}"
          }
        ],
        "verified": true,
        "name": "ESOPHAGUS",
        "diagnosis": [
          {
            "code": "NORMAL",
            "primary": true
          }
        ],
        "locationName": "RADIOLOGY MAIN FLOOR",
        "case": 43,
        "encounterName": "RADIOLOGY MAIN FLOOR Jan 15, 2004"
      },
      {
        "kind": "Imaging",
        "facilityCode": "500",
        "facilityName": "CAMP MASTER",
        "orderName": "CHEST 2 VIEWS PA&LAT",
        "statusName": "COMPLETE",
        "encounterUid": "urn:va:visit:9E7A:224:3817",
        "imagingTypeUid": "urn:va:imaging-Type:GENERAL RADIOLOGY",
        "locationUid": "urn:va:location:9E7A:40",
        "hasImages": false,
        "imageLocation": "RADIOLOGY MAIN FLOOR",
        "uid": "urn:va:image:9E7A:224:6959894.8599-1",
        "summary": "RADIOLOGIC EXAMINATION, CHEST, 2 VIEWS, FRONTAL AND LATERAL;",
        "pid": "C877;224",
        "localId": "6959894.8599-1",
        "typeName": "RADIOLOGIC EXAMINATION, CHEST, 2 VIEWS, FRONTAL AND LATERAL;",
        "dateTime": "200401051400",
        "category": "RA",
        "reason": "",
        "orderUid": "urn:va:order:9E7A:224:15738",
        "providers": [
          {
            "providerName": "LABTECH,SPECIAL",
            "providerDisplayName": "Labtech,Special",
            "summary": "ProcedureProvider{uid='null'}",
            "providerUid": "urn:va:user:9E7A:11745"
          }
        ],
        "providerName": "LABTECH,SPECIAL",
        "providerDisplayName": "Labtech,Special",
        "results": [
          {
            "localTitle": "CHEST 2 VIEWS PA&LAT",
            "uid": "urn:va:document:9E7A:224:6959894.8599-1",
            "summary": "ProcedureResult{uid='urn:va:document:9E7A:224:6959894.8599-1'}"
          }
        ],
        "verified": true,
        "name": "CHEST 2 VIEWS PA&LAT",
        "diagnosis": [
          {
            "code": "NORMAL",
            "primary": true
          }
        ],
        "locationName": "RADIOLOGY MAIN FLOOR",
        "case": 44,
        "encounterName": "RADIOLOGY MAIN FLOOR Jan 05, 2004"
      },
      {
        "kind": "Imaging",
        "facilityCode": "500",
        "facilityName": "CAMP BEE",
        "orderName": "CHEST 2 VIEWS PA&LAT",
        "statusName": "COMPLETE",
        "encounterUid": "urn:va:visit:C877:224:3817",
        "imagingTypeUid": "urn:va:imaging-Type:GENERAL RADIOLOGY",
        "locationUid": "urn:va:location:C877:40",
        "hasImages": false,
        "imageLocation": "RADIOLOGY MAIN FLOOR",
        "uid": "urn:va:image:C877:224:6959894.8599-1",
        "summary": "RADIOLOGIC EXAMINATION, CHEST, 2 VIEWS, FRONTAL AND LATERAL;",
        "pid": "C877;224",
        "localId": "6959894.8599-1",
        "typeName": "RADIOLOGIC EXAMINATION, CHEST, 2 VIEWS, FRONTAL AND LATERAL;",
        "dateTime": "200401051400",
        "category": "RA",
        "reason": "",
        "orderUid": "urn:va:order:C877:224:15738",
        "providers": [
          {
            "providerName": "LABTECH,SPECIAL",
            "providerDisplayName": "Labtech,Special",
            "summary": "ProcedureProvider{uid='null'}",
            "providerUid": "urn:va:user:C877:11745"
          }
        ],
        "providerName": "LABTECH,SPECIAL",
        "providerDisplayName": "Labtech,Special",
        "results": [
          {
            "localTitle": "CHEST 2 VIEWS PA&LAT",
            "uid": "urn:va:document:C877:224:6959894.8599-1",
            "summary": "ProcedureResult{uid='urn:va:document:C877:224:6959894.8599-1'}"
          }
        ],
        "verified": true,
        "name": "CHEST 2 VIEWS PA&LAT",
        "diagnosis": [
          {
            "code": "NORMAL",
            "primary": true
          }
        ],
        "locationName": "RADIOLOGY MAIN FLOOR",
        "case": 44,
        "encounterName": "RADIOLOGY MAIN FLOOR Jan 05, 2004"
      },
      {
        "kind": "Imaging",
        "facilityCode": "500",
        "facilityName": "CAMP MASTER",
        "orderName": "CHEST 2 VIEWS PA&LAT",
        "statusName": "COMPLETE",
        "encounterUid": "urn:va:visit:9E7A:224:3814",
        "imagingTypeUid": "urn:va:imaging-Type:GENERAL RADIOLOGY",
        "locationUid": "urn:va:location:9E7A:40",
        "hasImages": false,
        "imageLocation": "RADIOLOGY MAIN FLOOR",
        "uid": "urn:va:image:9E7A:224:6978892.8699-1",
        "summary": "RADIOLOGIC EXAMINATION, CHEST, 2 VIEWS, FRONTAL AND LATERAL;",
        "pid": "C877;224",
        "localId": "6978892.8699-1",
        "typeName": "RADIOLOGIC EXAMINATION, CHEST, 2 VIEWS, FRONTAL AND LATERAL;",
        "dateTime": "200211071300",
        "category": "RA",
        "reason": "",
        "orderUid": "urn:va:order:9E7A:224:15734",
        "providers": [
          {
            "providerName": "PROVIDER,FIFTY",
            "providerDisplayName": "Provider,Fifty",
            "summary": "ProcedureProvider{uid='null'}",
            "providerUid": "urn:va:user:9E7A:1595"
          }
        ],
        "providerName": "PROVIDER,FIFTY",
        "providerDisplayName": "Provider,Fifty",
        "results": [
          {
            "localTitle": "CHEST 2 VIEWS PA&LAT",
            "uid": "urn:va:document:9E7A:224:6978892.8699-1",
            "summary": "ProcedureResult{uid='urn:va:document:9E7A:224:6978892.8699-1'}"
          }
        ],
        "verified": true,
        "name": "CHEST 2 VIEWS PA&LAT",
        "locationName": "RADIOLOGY MAIN FLOOR",
        "case": 41,
        "encounterName": "RADIOLOGY MAIN FLOOR Nov 07, 2002"
      },
      {
        "kind": "Imaging",
        "facilityCode": "500",
        "facilityName": "CAMP BEE",
        "orderName": "CHEST 2 VIEWS PA&LAT",
        "statusName": "COMPLETE",
        "encounterUid": "urn:va:visit:C877:224:3814",
        "imagingTypeUid": "urn:va:imaging-Type:GENERAL RADIOLOGY",
        "locationUid": "urn:va:location:C877:40",
        "hasImages": false,
        "imageLocation": "RADIOLOGY MAIN FLOOR",
        "uid": "urn:va:image:C877:224:6978892.8699-1",
        "summary": "RADIOLOGIC EXAMINATION, CHEST, 2 VIEWS, FRONTAL AND LATERAL;",
        "pid": "C877;224",
        "localId": "6978892.8699-1",
        "typeName": "RADIOLOGIC EXAMINATION, CHEST, 2 VIEWS, FRONTAL AND LATERAL;",
        "dateTime": "200211071300",
        "category": "RA",
        "reason": "",
        "orderUid": "urn:va:order:C877:224:15734",
        "providers": [
          {
            "providerName": "PROVIDER,FIFTY",
            "providerDisplayName": "Provider,Fifty",
            "summary": "ProcedureProvider{uid='null'}",
            "providerUid": "urn:va:user:C877:1595"
          }
        ],
        "providerName": "PROVIDER,FIFTY",
        "providerDisplayName": "Provider,Fifty",
        "results": [
          {
            "localTitle": "CHEST 2 VIEWS PA&LAT",
            "uid": "urn:va:document:C877:224:6978892.8699-1",
            "summary": "ProcedureResult{uid='urn:va:document:C877:224:6978892.8699-1'}"
          }
        ],
        "verified": true,
        "name": "CHEST 2 VIEWS PA&LAT",
        "locationName": "RADIOLOGY MAIN FLOOR",
        "case": 41,
        "encounterName": "RADIOLOGY MAIN FLOOR Nov 07, 2002"
      },
      {
        "kind": "Imaging",
        "facilityCode": "500",
        "facilityName": "CAMP MASTER",
        "orderName": "HIP 2 OR MORE VIEWS",
        "statusName": "COMPLETE",
        "encounterUid": "urn:va:visit:9E7A:224:3815",
        "imagingTypeUid": "urn:va:imaging-Type:GENERAL RADIOLOGY",
        "locationUid": "urn:va:location:9E7A:40",
        "hasImages": false,
        "imageLocation": "RADIOLOGY MAIN FLOOR",
        "uid": "urn:va:image:9E7A:224:6979785.9099-1",
        "summary": "RADIOLOGIC EXAMINATION, HIP, UNILATERAL; COMPLETE, MINIMUM OF 2 VIEWS",
        "pid": "C877;224",
        "localId": "6979785.9099-1",
        "typeName": "RADIOLOGIC EXAMINATION, HIP, UNILATERAL; COMPLETE, MINIMUM OF 2 VIEWS",
        "dateTime": "200202140900",
        "category": "RA",
        "reason": "",
        "orderUid": "urn:va:order:9E7A:224:15735",
        "providers": [
          {
            "providerName": "LABTECH,SPECIAL",
            "providerDisplayName": "Labtech,Special",
            "summary": "ProcedureProvider{uid='null'}",
            "providerUid": "urn:va:user:9E7A:11745"
          }
        ],
        "providerName": "LABTECH,SPECIAL",
        "providerDisplayName": "Labtech,Special",
        "results": [
          {
            "localTitle": "HIP 2 OR MORE VIEWS",
            "uid": "urn:va:document:9E7A:224:6979785.9099-1",
            "summary": "ProcedureResult{uid='urn:va:document:9E7A:224:6979785.9099-1'}"
          }
        ],
        "verified": true,
        "name": "HIP 2 OR MORE VIEWS",
        "diagnosis": [
          {
            "code": "MINOR ABNORMALITY",
            "primary": true
          }
        ],
        "locationName": "RADIOLOGY MAIN FLOOR",
        "case": 42,
        "encounterName": "RADIOLOGY MAIN FLOOR Feb 14, 2002"
      },
      {
        "kind": "Imaging",
        "facilityCode": "500",
        "facilityName": "CAMP BEE",
        "orderName": "HIP 2 OR MORE VIEWS",
        "statusName": "COMPLETE",
        "encounterUid": "urn:va:visit:C877:224:3815",
        "imagingTypeUid": "urn:va:imaging-Type:GENERAL RADIOLOGY",
        "locationUid": "urn:va:location:C877:40",
        "hasImages": false,
        "imageLocation": "RADIOLOGY MAIN FLOOR",
        "uid": "urn:va:image:C877:224:6979785.9099-1",
        "summary": "RADIOLOGIC EXAMINATION, HIP, UNILATERAL; COMPLETE, MINIMUM OF 2 VIEWS",
        "pid": "C877;224",
        "localId": "6979785.9099-1",
        "typeName": "RADIOLOGIC EXAMINATION, HIP, UNILATERAL; COMPLETE, MINIMUM OF 2 VIEWS",
        "dateTime": "200202140900",
        "category": "RA",
        "reason": "",
        "orderUid": "urn:va:order:C877:224:15735",
        "providers": [
          {
            "providerName": "LABTECH,SPECIAL",
            "providerDisplayName": "Labtech,Special",
            "summary": "ProcedureProvider{uid='null'}",
            "providerUid": "urn:va:user:C877:11745"
          }
        ],
        "providerName": "LABTECH,SPECIAL",
        "providerDisplayName": "Labtech,Special",
        "results": [
          {
            "localTitle": "HIP 2 OR MORE VIEWS",
            "uid": "urn:va:document:C877:224:6979785.9099-1",
            "summary": "ProcedureResult{uid='urn:va:document:C877:224:6979785.9099-1'}"
          }
        ],
        "verified": true,
        "name": "HIP 2 OR MORE VIEWS",
        "diagnosis": [
          {
            "code": "MINOR ABNORMALITY",
            "primary": true
          }
        ],
        "locationName": "RADIOLOGY MAIN FLOOR",
        "case": 42,
        "encounterName": "RADIOLOGY MAIN FLOOR Feb 14, 2002"
      },
      {
        "kind": "Imaging",
        "facilityCode": "998",
        "facilityName": "ABILENE (CAA)",
        "orderName": "BONE DENSITY STUDY, DUAL PHOTON ABSORPTIOMETRY",
        "statusName": "COMPLETE",
        "imagingTypeUid": "urn:va:imaging-Type:NUCLEAR MEDICINE",
        "locationUid": "urn:va:location:9E7A:114",
        "hasImages": false,
        "imageLocation": "NUCLEAR MEDICINE",
        "uid": "urn:va:image:9E7A:224:7059377.8748-1",
        "summary": "BONE DENSITY (BONE MINERAL CONTENT) STUDY, 1 OR MORE SITES; DUAL PHOTON ABSORPTIOMETRY, 1 OR MORE SITES",
        "pid": "C877;224",
        "localId": "7059377.8748-1",
        "typeName": "BONE DENSITY (BONE MINERAL CONTENT) STUDY, 1 OR MORE SITES; DUAL PHOTON ABSORPTIOMETRY, 1 OR MORE SITES",
        "dateTime": "199406221251",
        "category": "RA",
        "reason": "",
        "orderUid": "urn:va:order:9E7A:224:1481.1",
        "name": "BONE DENSITY STUDY, DUAL PHOTON ABSORPTIOMETRY",
        "locationName": "NUCLEAR MEDICINE",
        "case": 77
      },
      {
        "kind": "Imaging",
        "facilityCode": "998",
        "facilityName": "ABILENE (CAA)",
        "orderName": "BONE DENSITY STUDY, DUAL PHOTON ABSORPTIOMETRY",
        "statusName": "COMPLETE",
        "imagingTypeUid": "urn:va:imaging-Type:NUCLEAR MEDICINE",
        "locationUid": "urn:va:location:C877:114",
        "hasImages": false,
        "imageLocation": "NUCLEAR MEDICINE",
        "uid": "urn:va:image:C877:224:7059377.8748-1",
        "summary": "BONE DENSITY (BONE MINERAL CONTENT) STUDY, 1 OR MORE SITES; DUAL PHOTON ABSORPTIOMETRY, 1 OR MORE SITES",
        "pid": "C877;224",
        "localId": "7059377.8748-1",
        "typeName": "BONE DENSITY (BONE MINERAL CONTENT) STUDY, 1 OR MORE SITES; DUAL PHOTON ABSORPTIOMETRY, 1 OR MORE SITES",
        "dateTime": "199406221251",
        "category": "RA",
        "reason": "",
        "orderUid": "urn:va:order:C877:224:1481.1",
        "name": "BONE DENSITY STUDY, DUAL PHOTON ABSORPTIOMETRY",
        "locationName": "NUCLEAR MEDICINE",
        "case": 77
      },
      {
        "kind": "Imaging",
        "facilityCode": "500",
        "facilityName": "CAMP MASTER",
        "statusName": "COMPLETE",
        "imagingTypeUid": "urn:va:imaging-Type:GENERAL RADIOLOGY",
        "locationUid": "urn:va:location:9E7A:40",
        "hasImages": false,
        "imageLocation": "RADIOLOGY MAIN FLOOR",
        "uid": "urn:va:image:9E7A:224:7059378.9199-1",
        "summary": "RADIOLOGIC EXAMINATION; FOREARM, 2 VIEWS",
        "pid": "C877;224",
        "localId": "7059378.9199-1",
        "typeName": "RADIOLOGIC EXAMINATION; FOREARM, 2 VIEWS",
        "dateTime": "199406210800",
        "category": "RA",
        "reason": "",
        "name": "FOREARM 2 VIEWS",
        "locationName": "RADIOLOGY MAIN FLOOR",
        "case": 78
      },
      {
        "kind": "Imaging",
        "facilityCode": "500",
        "facilityName": "CAMP BEE",
        "statusName": "COMPLETE",
        "imagingTypeUid": "urn:va:imaging-Type:GENERAL RADIOLOGY",
        "locationUid": "urn:va:location:C877:40",
        "hasImages": false,
        "imageLocation": "RADIOLOGY MAIN FLOOR",
        "uid": "urn:va:image:C877:224:7059378.9199-1",
        "summary": "RADIOLOGIC EXAMINATION; FOREARM, 2 VIEWS",
        "pid": "C877;224",
        "localId": "7059378.9199-1",
        "typeName": "RADIOLOGIC EXAMINATION; FOREARM, 2 VIEWS",
        "dateTime": "199406210800",
        "category": "RA",
        "reason": "",
        "name": "FOREARM 2 VIEWS",
        "locationName": "RADIOLOGY MAIN FLOOR",
        "case": 78
      },
      {
        "kind": "Imaging",
        "facilityCode": "500",
        "facilityName": "CAMP MASTER",
        "statusName": "COMPLETE",
        "imagingTypeUid": "urn:va:imaging-Type:GENERAL RADIOLOGY",
        "locationUid": "urn:va:location:9E7A:40",
        "hasImages": false,
        "imageLocation": "RADIOLOGY MAIN FLOOR",
        "uid": "urn:va:image:9E7A:224:7059382.8392-1",
        "summary": "RADIOLOGIC EXAMINATION, ANKLE, ARTHROGRAPHY, RADIOLOGICAL SUPERVISION AND INTERPRETATION",
        "pid": "C877;224",
        "localId": "7059382.8392-1",
        "typeName": "RADIOLOGIC EXAMINATION, ANKLE, ARTHROGRAPHY, RADIOLOGICAL SUPERVISION AND INTERPRETATION",
        "dateTime": "199406171607",
        "category": "RA",
        "reason": "",
        "name": "ARTHROGRAM ANKLE S&I",
        "locationName": "RADIOLOGY MAIN FLOOR",
        "case": 83
      },
      {
        "kind": "Imaging",
        "facilityCode": "500",
        "facilityName": "CAMP BEE",
        "statusName": "COMPLETE",
        "imagingTypeUid": "urn:va:imaging-Type:GENERAL RADIOLOGY",
        "locationUid": "urn:va:location:C877:40",
        "hasImages": false,
        "imageLocation": "RADIOLOGY MAIN FLOOR",
        "uid": "urn:va:image:C877:224:7059382.8392-1",
        "summary": "RADIOLOGIC EXAMINATION, ANKLE, ARTHROGRAPHY, RADIOLOGICAL SUPERVISION AND INTERPRETATION",
        "pid": "C877;224",
        "localId": "7059382.8392-1",
        "typeName": "RADIOLOGIC EXAMINATION, ANKLE, ARTHROGRAPHY, RADIOLOGICAL SUPERVISION AND INTERPRETATION",
        "dateTime": "199406171607",
        "category": "RA",
        "reason": "",
        "name": "ARTHROGRAM ANKLE S&I",
        "locationName": "RADIOLOGY MAIN FLOOR",
        "case": 83
      },
      {
        "kind": "Imaging",
        "facilityCode": "500",
        "facilityName": "CAMP MASTER",
        "statusName": "COMPLETE",
        "imagingTypeUid": "urn:va:imaging-Type:GENERAL RADIOLOGY",
        "locationUid": "urn:va:location:9E7A:40",
        "hasImages": false,
        "imageLocation": "RADIOLOGY MAIN FLOOR",
        "uid": "urn:va:image:9E7A:224:7059382.8469-1",
        "summary": "RADIOLOGIC EXAMINATION, ANKLE; 2 VIEWS",
        "pid": "C877;224",
        "localId": "7059382.8469-1",
        "typeName": "RADIOLOGIC EXAMINATION, ANKLE; 2 VIEWS",
        "dateTime": "199406171530",
        "category": "RA",
        "reason": "",
        "providers": [
          {
            "providerName": "PROGRAMMER,TWENTY",
            "providerDisplayName": "Programmer,Twenty",
            "summary": "ProcedureProvider{uid='null'}",
            "providerUid": "urn:va:user:9E7A:755"
          }
        ],
        "providerName": "PROGRAMMER,TWENTY",
        "providerDisplayName": "Programmer,Twenty",
        "results": [
          {
            "localTitle": "ANKLE 2 VIEWS",
            "uid": "urn:va:document:9E7A:224:7059382.8469-1",
            "summary": "ProcedureResult{uid='urn:va:document:9E7A:224:7059382.8469-1'}"
          }
        ],
        "verified": true,
        "name": "ANKLE 2 VIEWS",
        "diagnosis": [
          {
            "code": "NORMAL",
            "primary": true
          }
        ],
        "locationName": "RADIOLOGY MAIN FLOOR",
        "case": 79
      },
      {
        "kind": "Imaging",
        "facilityCode": "500",
        "facilityName": "CAMP BEE",
        "statusName": "COMPLETE",
        "imagingTypeUid": "urn:va:imaging-Type:GENERAL RADIOLOGY",
        "locationUid": "urn:va:location:C877:40",
        "hasImages": false,
        "imageLocation": "RADIOLOGY MAIN FLOOR",
        "uid": "urn:va:image:C877:224:7059382.8469-1",
        "summary": "RADIOLOGIC EXAMINATION, ANKLE; 2 VIEWS",
        "pid": "C877;224",
        "localId": "7059382.8469-1",
        "typeName": "RADIOLOGIC EXAMINATION, ANKLE; 2 VIEWS",
        "dateTime": "199406171530",
        "category": "RA",
        "reason": "",
        "providers": [
          {
            "providerName": "PROGRAMMER,TWENTY",
            "providerDisplayName": "Programmer,Twenty",
            "summary": "ProcedureProvider{uid='null'}",
            "providerUid": "urn:va:user:C877:755"
          }
        ],
        "providerName": "PROGRAMMER,TWENTY",
        "providerDisplayName": "Programmer,Twenty",
        "results": [
          {
            "localTitle": "ANKLE 2 VIEWS",
            "uid": "urn:va:document:C877:224:7059382.8469-1",
            "summary": "ProcedureResult{uid='urn:va:document:C877:224:7059382.8469-1'}"
          }
        ],
        "verified": true,
        "name": "ANKLE 2 VIEWS",
        "diagnosis": [
          {
            "code": "NORMAL",
            "primary": true
          }
        ],
        "locationName": "RADIOLOGY MAIN FLOOR",
        "case": 79
      }
    ]
  }
}